uvfiles/__init__.py
uvfiles/py.typed
uvfiles-0.0.1.dist-info/WHEEL
uvfiles-0.0.1.dist-info/METADATA
uvfiles-0.0.1.dist-info/RECORD
