Metadata-Version: 2.3
Name: uvfiles
Version: 0.0.1
Summary: Add your description here
Author: AN Long
Author-email: AN Long <aisk1988@gmail.com>
Requires-Dist: uvloop
Requires-Python: >=3.10
